aerodrome_mcp/__init__.py
aerodrome_mcp/server.py
aerodrome_swap_mcp-0.1.1.dist-info/METADATA
aerodrome_swap_mcp-0.1.1.dist-info/WHEEL
aerodrome_swap_mcp-0.1.1.dist-info/entry_points.txt
aerodrome_swap_mcp-0.1.1.dist-info/top_level.txt
aerodrome_swap_mcp-0.1.1.dist-info/RECORD
