Metadata-Version: 2.4
Name: aerodrome-swap-mcp
Version: 0.1.1
Summary: MCP server for Aerodrome Swap API
Home-page: https://github.com/protagolabs/aerodrome-swap-mcp
Author: Aerodrome Swap Team
Author-email: yi.zhou@netmind.ai
Classifier: Programming Language :: Python :: 3
Classifier: License :: OSI Approved :: MIT License
Classifier: Operating System :: OS Independent
Requires-Python: >=3.8
Requires-Dist: fastmcp>=0.1.0
Requires-Dist: requests>=2.28.0
Requires-Dist: pydantic>=2.0.0
Dynamic: author
Dynamic: author-email
Dynamic: classifier
Dynamic: description
Dynamic: description-content-type
Dynamic: home-page
Dynamic: requires-dist
Dynamic: requires-python
Dynamic: summary
